cassette/__init__.py
cassette/main.py
cassette/commands/__init__.py
cassette/commands/list_jobs.py
cassette/commands/run.py
cassette/jobs/__init__.py
cassette/jobs/job_describe/Describe.py
cassette/jobs/job_describe/__init__.py
cassette/jobs/job_describe/jtask.py
cassette/jobs/job_gettimeline/Gettimeline.py
cassette/jobs/job_gettimeline/TimelineTemplate.py
cassette/jobs/job_gettimeline/__init__.py
cassette/jobs/job_gettimeline/jtask.py
cassette/jobs/job_load/Load.py
cassette/jobs/job_load/__init__.py
cassette/jobs/job_load/dbjob.py
cassette/jobs/job_load/jtask.py
cassette/jobs/job_load/loadjob.py
cassette/jobs/job_loadtimeline/Loadtimeline.py
cassette/jobs/job_loadtimeline/__init__.py
cassette/jobs/job_loadtimeline/dbjob.py
cassette/jobs/job_loadtimeline/jtask.py
cassette/jobs/job_loadtimeline/loadjob.py
cassette/jobs/job_renderaudio/Renderaudio.py
cassette/jobs/job_renderaudio/__init__.py
cassette/jobs/job_renderaudio/jtask.py
cassette/jobs/job_renderrecord/Renderrecord.py
cassette/jobs/job_renderrecord/__init__.py
cassette/jobs/job_renderrecord/jtask.py
cassette/jobs/job_renderscene/Renderscene.py
cassette/jobs/job_renderscene/__init__.py
cassette/jobs/job_renderscene/jtask.py
cassette/jobs/job_test/Test.py
cassette/jobs/job_test/__init__.py
cassette/jobs/job_test/jtask.py
cassette/lib/Descriptor.py
cassette/lib/Fountain.py
cassette/lib/__init__.py
cassette/lib/character/CharacterAudio.py
cassette/lib/character/CharacterAudioRender.py
cassette/lib/character/__init__.py
cassette/lib/mixer/AudioMixer.py
cassette/lib/mixer/__init__.py
cassette/lib/scene/SceneAudioRender.py
cassette/lib/scene/__init__.py
cassette/utils/.env
cassette/utils/EnvConfig.py
cassette/utils/Job.py
cassette/utils/ModuleRunner.py
cassette/utils/__init__.py
alpezacassette-0.1.6.dist-info/LICENSE
alpezacassette-0.1.6.dist-info/METADATA
alpezacassette-0.1.6.dist-info/WHEEL
alpezacassette-0.1.6.dist-info/entry_points.txt
alpezacassette-0.1.6.dist-info/top_level.txt
alpezacassette-0.1.6.dist-info/RECORD
