Metadata-Version: 2.1
Name: alpezacassette
Version: 0.1.6
Summary: Renderizador de dialogos .fountain a audio
Home-page: https://github.com/alpeza/cassette
Author: alpeza
License-File: LICENSE
